src/__init__.py
src/agent/__init__.py
src/agent/agent.py
src/agent/checkpointer.py
src/agent/formatting/__init__.py
src/agent/formatting/build_review_context.py
src/agent/formatting/format_file_lines.py
src/agent/formatting/format_review_content.py
src/agent/formatting/format_verification.py
src/agent/formatting/render_structured_output.py
src/agent/git_utils/__init__.py
src/agent/git_utils/get_changed_files.py
src/agent/git_utils/get_commit_messages.py
src/agent/git_utils/get_current_branch.py
src/agent/git_utils/get_file_diff.py
src/agent/git_utils/get_repo_root.py
src/agent/git_utils/types.py
src/agent/middleware/__init__.py
src/agent/middleware/recursion_guard.py
src/agent/middleware/summarizing_middleware.py
src/agent/model.py
src/agent/progress_callback_handler.py
src/agent/prompts/__init__.py
src/agent/prompts/context_summary.md
src/agent/prompts/full_review.md
src/agent/prompts/last_step.md
src/agent/prompts/verify_answers.md
src/agent/prompts/verify_questions.md
src/agent/prompts/verify_score.md
src/agent/providers/__init__.py
src/agent/providers/anthropic.py
src/agent/providers/bedrock.py
src/agent/providers/bedrock_caching.py
src/agent/providers/moonshot.py
src/agent/providers/ollama.py
src/agent/runner.py
src/agent/schema.py
src/agent/token_usage.py
src/agent/tools/__init__.py
src/agent/tools/file_context.py
src/agent/tools/list_files.py
src/agent/tools/read_file_part.py
src/agent/tools/search_in_files.py
src/agent/verification/__init__.py
src/agent/verification/agent.py
src/agent/verification/helpers.py
src/agent/verification/runner.py
src/agent/verification/schema.py
src/config.py
src/main.py
reviewcerberus-1.3.1.dist-info/METADATA
reviewcerberus-1.3.1.dist-info/WHEEL
reviewcerberus-1.3.1.dist-info/entry_points.txt
reviewcerberus-1.3.1.dist-info/licenses/LICENSE
reviewcerberus-1.3.1.dist-info/RECORD
