Metadata-Version: 2.4
Name: reviewcerberus
Version: 1.3.1
Summary: AI-powered code review tool for git branches
License: MIT
License-File: LICENSE
Keywords: code-review,ai,git,langchain,llm,anthropic,claude,automation
Author: Kirill
Author-email: kirill89@gmail.com
Requires-Python: >=3.11,<4.0
Classifier: Development Status :: 4 - Beta
Classifier: Environment :: Console
Classifier: Intended Audience :: Developers
Classifier: License :: OSI Approved :: MIT License
Classifier: Operating System :: OS Independent
Classifier: Programming Language :: Python :: 3
Classifier: Programming Language :: Python :: 3.11
Classifier: Programming Language :: Python :: 3.12
Classifier: Programming Language :: Python :: 3.13
Classifier: Programming Language :: Python :: 3.14
Classifier: Topic :: Software Development :: Quality Assurance
Classifier: Topic :: Software Development :: Version Control :: Git
Requires-Dist: boto3 (==1.42.15)
Requires-Dist: langchain (==1.2.0)
Requires-Dist: langchain-anthropic (==1.3.0)
Requires-Dist: langchain-aws (==1.1.0)
Requires-Dist: langchain-ollama (==1.0.1)
Requires-Dist: langchain-openai (==1.1.7)
Requires-Dist: mdformat (==1.0.0)
Requires-Dist: mdformat-gfm (==1.0.0)
Requires-Dist: python-dotenv (==1.2.1)
Requires-Dist: requests (==2.32.5)
Project-URL: Homepage, https://github.com/Kirill89/reviewcerberus
Project-URL: Repository, https://github.com/Kirill89/reviewcerberus
